Metadata-Version: 1.0
Name: dai175-probability
Version: 0.1
Summary: Gaussian and Binomial distributions
Home-page: UNKNOWN
Author: Daisuke Ohba
Author-email: dai175dai@gmail.com
License: UNKNOWN
Platform: UNKNOWN
